add/__init__.py
add/adding.py
add_abedelnabi/__init__.py
add_abedelnabi/adding.py
add_abedelnabi-0.1.0.dist-info/LICENSE
add_abedelnabi-0.1.0.dist-info/METADATA
add_abedelnabi-0.1.0.dist-info/WHEEL
add_abedelnabi-0.1.0.dist-info/top_level.txt
add_abedelnabi-0.1.0.dist-info/RECORD
