Metadata-Version: 2.1
Name: add-abedelnabi
Version: 0.1.0
Summary: A package for adding two numbers together
Author: Mohammad Usama
License-File: LICENSE
